obgraph/variant_to_nodes.py
obgraph/haplotype_nodes.py
obgraph/traversing.py
obgraph/position_id.py
obgraph/haplotype_matrix.py
obgraph/variants.py
obgraph/cython_traversing.cpython-38-x86_64-linux-gnu.so
obgraph/dummy_node_adder.py
obgraph/coordinate_converter.py
obgraph/neighbour_haplotype_nodes.py
obgraph/graph_merger.py
obgraph/__init__.py
obgraph/nplist.py
obgraph/gfa.py
obgraph/graph.py
obgraph/numpy_variants.py
obgraph/command_line_interface.py
obgraph/util.py
obgraph/genotype_matrix.py
obgraph/mutable_graph.py
obgraph/graph_construction.py
obgraph-0.0.30.dist-info/METADATA
obgraph-0.0.30.dist-info/RECORD
obgraph-0.0.30.dist-info/top_level.txt
obgraph-0.0.30.dist-info/WHEEL
obgraph-0.0.30.dist-info/entry_points.txt
