Metadata-Version: 2.1
Name: obgraph
Version: 0.0.30
Summary: obgraph
Home-page: http://github.com/ivargr/obgraph
Author: Ivar Grytten
Author-email: UNKNOWN
License: MIT
Platform: UNKNOWN
Classifier: Programming Language :: Python :: 3
Requires-Dist: bionumpy
Requires-Dist: cython
Requires-Dist: numpy
Requires-Dist: pathos
Requires-Dist: shared-memory-wrapper (>=0.0.18)
Requires-Dist: tqdm
